{"StarRise_V3":{"run_id":"0398a8d92b6eebcaa5796fa38293530a7b8475d5","backtest_start_time":1723735185,"timeframe":"5m","timeframe_detail":"1m","backtest_start_ts":1714521600,"backtest_end_ts":1717200000},"StarRise":{"run_id":"b7530f47221f37110c1d9d44a14c238a79d7d7ff","backtest_start_time":1723735209,"timeframe":"5m","timeframe_detail":"1m","backtest_start_ts":1714521600,"backtest_end_ts":1717200000},"StarRise_strat":{"run_id":"c88af92c08ca81d8db8333768352164765f30e34","backtest_start_time":1723735227,"timeframe":"5m","timeframe_detail":"1m","backtest_start_ts":1714521600,"backtest_end_ts":1717200000}}