{"strategy":{"Simple":{"trades":[{"pair":"PEPE/USDT","stake_amount":98.9999997,"max_stake_amount":98.9999997,"amount":14887218.0,"open_date":"2024-05-01 03:15:00+00:00","close_date":"2024-05-01 03:39:00+00:00","open_rate":6.65e-06,"close_rate":6.729879879879879e-06,"fee_open":0.001,"fee_close":0.001,"trade_duration":24,"profit_ratio":0.009990010020282747,"profit_abs":0.99,"exit_reason":"roi","initial_stop_loss_abs":4.99e-06,"initial_stop_loss_ratio":-0.25,"stop_loss_abs":4.99e-06,"stop_loss_ratio":-0.25,"min_rate":6.61e-06,"max_rate":6.73e-06,"is_open":false,"enter_tag":"","leverage":1.0,"is_short":false,"open_timestamp":1714533300000,"close_timestamp":1714534740000,"orders":[{"amount":14887218.0,"safe_price":6.65e-06,"ft_order_side":"buy","order_filled_timestamp":1714533300000,"ft_is_entry":true,"ft_order_tag":""},{"amount":14887218.0,"safe_price":6.729879879879879e-06,"ft_order_side":"sell","order_filled_timestamp":1714534740000,"ft_is_entry":false,"ft_order_tag":"roi"}]},{"pair":"FTM/USDT","stake_amount":98.97,"max_stake_amount":98.97,"amount":150.0,"open_date":"2024-05-01 03:10:00+00:00","close_date":"2024-05-01 04:00:00+00:00","open_rate":0.6598,"close_rate":0.6677255255255254,"fee_open":0.001,"fee_close":0.001,"trade_duration":50,"profit_ratio":0.009990009990009992,"profit_abs":0.9897,"exit_reason":"roi","initial_stop_loss_abs":0.4949,"initial_stop_loss_ratio":-0.25,"stop_loss_abs":0.4949,"stop_loss_ratio":-0.25,"min_rate":0.6559,"max_rate":0.6678,"is_open":false,"enter_tag":"","leverage":1.0,"is_short":false,"open_timestamp":1714533000000,"close_timestamp":1714536000000,"orders":[{"amount":150.0,"safe_price":0.6598,"ft_order_side":"buy","order_filled_timestamp":1714533000000,"ft_is_entry":true,"ft_order_tag":""},{"amount":150.0,"safe_price":0.6677255255255254,"ft_order_side":"sell","order_filled_timestamp":1714536000000,"ft_is_entry":false,"ft_order_tag":"roi"}]},{"pair":"ATOM/USDT","stake_amount":99.0525,"max_stake_amount":99.0525,"amount":11.75,"open_date":"2024-05-01 03:35:00+00:00","close_date":"2024-05-01 04:11:00+00:00","open_rate":8.43,"close_rate":8.53126126126126,"fee_open":0.001,"fee_close":0.001,"trade_duration":36,"profit_ratio":0.00999000999000999,"profit_abs":0.990525,"exit_reason":"roi","initial_stop_loss_abs":6.323,"initial_stop_loss_ratio":-0.25,"stop_loss_abs":6.323,"stop_loss_ratio":-0.25,"min_rate":8.42,"max_rate":8.532,"is_open":false,"enter_tag":"","leverage":1.0,"is_short":false,"open_timestamp":1714534500000,"close_timestamp":1714536660000,"orders":[{"amount":11.75,"safe_price":8.43,"ft_order_side":"buy","order_filled_timestamp":1714534500000,"ft_is_entry":true,"ft_order_tag":""},{"amount":11.75,"safe_price":8.53126126126126,"ft_order_side":"sell","order_filled_timestamp":1714536660000,"ft_is_entry":false,"ft_order_tag":"roi"}]},{"pair":"DOT/USDT","stake_amount":98.98252,"max_stake_amount":98.98252,"amount":15.32,"open_date":"2024-05-01 03:05:00+00:00","close_date":"2024-05-01 04:35:00+00:00","open_rate":6.461,"close_rate":6.538609609609609,"fee_open":0.001,"fee_close":0.001,"trade_duration":90,"profit_ratio":0.00999000999000999,"profit_abs":0.9898252,"exit_reason":"roi","initial_stop_loss_abs":4.846,"initial_stop_loss_ratio":-0.25,"stop_loss_abs":4.846,"stop_loss_ratio":-0.25,"min_rate":6.412,"max_rate":6.543,"is_open":false,"enter_tag":"","leverage":1.0,"is_short":false,"open_timestamp":1714532700000,"close_timestamp":1714538100000,"orders":[{"amount":15.32,"safe_price":6.461,"ft_order_side":"buy","order_filled_timestamp":1714532700000,"ft_is_entry":true,"ft_order_tag":""},{"amount":15.32,"safe_price":6.538609609609609,"ft_order_side":"sell","order_filled_timestamp":1714538100000,"ft_is_entry":false,"ft_order_tag":"roi"}]},{"pair":"ARB/USDT","stake_amount":99.25288,"max_stake_amount":99.25288,"amount":96.7,"open_date":"2024-05-01 04:10:00+00:00","close_date":"2024-05-01 04:54:00+00:00","open_rate":1.0264,"close_rate":1.0387291291291292,"fee_open":0.001,"fee_close":0.001,"trade_duration":44,"profit_ratio":0.00999000999000999,"profit_abs":0.9925288,"exit_reason":"roi","initial_stop_loss_abs":0.7698,"initial_stop_loss_ratio":-0.25,"stop_loss_abs":0.7698,"stop_loss_ratio":-0.25,"min_rate":1.0246,"max_rate":1.0404,"is_open":false,"enter_tag":"","leverage":1.0,"is_short":false,"open_timestamp":1714536600000,"close_timestamp":1714539240000,"orders":[{"amount":96.7,"safe_price":1.0264,"ft_order_side":"buy","order_filled_timestamp":1714536600000,"ft_is_entry":true,"ft_order_tag":""},{"amount":96.7,"safe_price":1.0387291291291292,"ft_order_side":"sell","order_filled_timestamp":1714539240000,"ft_is_entry":false,"ft_order_tag":"roi"}]},{"pair":"ADA/USDT","stake_amount":99.36682,"max_stake_amount":99.36682,"amount":223.9,"open_date":"2024-05-01 04:35:00+00:00","close_date":"2024-05-01 13:10:00+00:00","open_rate":0.4438,"close_rate":0.4428,"fee_open":0.001,"fee_close":0.001,"trade_duration":515,"profit_ratio":-0.004246767203053818,"profit_abs":-0.42240974,"exit_reason":"exit_signal","initial_stop_loss_abs":0.3329,"initial_stop_loss_ratio":-0.25,"stop_loss_abs":0.3329,"stop_loss_ratio":-0.25,"min_rate":0.4184,"max_rate":0.4446,"is_open":false,"enter_tag":"","leverage":1.0,"is_short":false,"open_timestamp":1714538100000,"close_timestamp":1714569000000,"orders":[{"amount":223.9,"safe_price":0.4438,"ft_order_side":"buy","order_filled_timestamp":1714538100000,"ft_is_entry":true,"ft_order_tag":""},{"amount":223.9,"safe_price":0.4428,"ft_order_side":"sell","order_filled_timestamp":1714569000000,"ft_is_entry":false,"ft_order_tag":"exit_signal"}]},{"pair":"AVAX/USDT","stake_amount":99.4194,"max_stake_amount":99.4194,"amount":3.06,"open_date":"2024-05-01 13:10:00+00:00","close_date":"2024-05-01 14:55:00+00:00","open_rate":32.49,"close_rate":32.880270270270266,"fee_open":0.001,"fee_close":0.001,"trade_duration":105,"profit_ratio":0.00999000999000999,"profit_abs":0.994194,"exit_reason":"roi","initial_stop_loss_abs":24.37,"initial_stop_loss_ratio":-0.25,"stop_loss_abs":24.37,"stop_loss_ratio":-0.25,"min_rate":32.18,"max_rate":33.01,"is_open":false,"enter_tag":"","leverage":1.0,"is_short":false,"open_timestamp":1714569000000,"close_timestamp":1714575300000,"orders":[{"amount":3.06,"safe_price":32.49,"ft_order_side":"buy","order_filled_timestamp":1714569000000,"ft_is_entry":true,"ft_order_tag":""},{"amount":3.06,"safe_price":32.880270270270266,"ft_order_side":"sell","order_filled_timestamp":1714575300000,"ft_is_entry":false,"ft_order_tag":"roi"}]},{"pair":"LTC/USDT","stake_amount":99.51068,"max_stake_amount":99.51068,"amount":1.286,"open_date":"2024-05-01 15:00:00+00:00","close_date":"2024-05-01 17:46:00+00:00","open_rate":77.38,"close_rate":78.30948948948947,"fee_open":0.001,"fee_close":0.001,"trade_duration":166,"profit_ratio":0.00999000999000999,"profit_abs":0.9951068,"exit_reason":"roi","initial_stop_loss_abs":58.04,"initial_stop_loss_ratio":-0.25,"stop_loss_abs":58.04,"stop_loss_ratio":-0.25,"min_rate":76.52,"max_rate":78.36,"is_open":false,"enter_tag":"","leverage":1.0,"is_short":false,"open_timestamp":1714575600000,"close_timestamp":1714585560000,"orders":[{"amount":1.286,"safe_price":77.38,"ft_order_side":"buy","order_filled_timestamp":1714575600000,"ft_is_entry":true,"ft_order_tag":""},{"amount":1.286,"safe_price":78.30948948948947,"ft_order_side":"sell","order_filled_timestamp":1714585560000,"ft_is_entry":false,"ft_order_tag":"roi"}]},{"pair":"BURGER/USDT","stake_amount":99.6156,"max_stake_amount":99.6156,"amount":236.0,"open_date":"2024-05-01 17:45:00+00:00","close_date":"2024-05-01 18:01:00+00:00","open_rate":0.4221,"close_rate":0.4271702702702702,"fee_open":0.001,"fee_close":0.001,"trade_duration":16,"profit_ratio":0.009990009990009992,"profit_abs":0.996156,"exit_reason":"roi","initial_stop_loss_abs":0.3166,"initial_stop_loss_ratio":-0.25,"stop_loss_abs":0.3166,"stop_loss_ratio":-0.25,"min_rate":0.422,"max_rate":0.4274,"is_open":false,"enter_tag":"","leverage":1.0,"is_short":false,"open_timestamp":1714585500000,"close_timestamp":1714586460000,"orders":[{"amount":236.0,"safe_price":0.4221,"ft_order_side":"buy","order_filled_timestamp":1714585500000,"ft_is_entry":true,"ft_order_tag":""},{"amount":236.0,"safe_price":0.4271702702702702,"ft_order_side":"sell","order_filled_timestamp":1714586460000,"ft_is_entry":false,"ft_order_tag":"roi"}]},{"pair":"ADA/USDT","stake_amount":99.7326,"max_stake_amount":99.7326,"amount":227.7,"open_date":"2024-05-01 18:00:00+00:00","close_date":"2024-05-01 18:03:00+00:00","open_rate":0.438,"close_rate":0.4432612612612612,"fee_open":0.001,"fee_close":0.001,"trade_duration":3,"profit_ratio":0.00999000999000999,"profit_abs":0.997326,"exit_reason":"roi","initial_stop_loss_abs":0.3285,"initial_stop_loss_ratio":-0.25,"stop_loss_abs":0.3285,"stop_loss_ratio":-0.25,"min_rate":0.438,"max_rate":0.4439,"is_open":false,"enter_tag":"","leverage":1.0,"is_short":false,"open_timestamp":1714586400000,"close_timestamp":1714586580000,"orders":[{"amount":227.7,"safe_price":0.438,"ft_order_side":"buy","order_filled_timestamp":1714586400000,"ft_is_entry":true,"ft_order_tag":""},{"amount":227.7,"safe_price":0.4432612612612612,"ft_order_side":"sell","order_filled_timestamp":1714586580000,"ft_is_entry":false,"ft_order_tag":"roi"}]},{"pair":"PEOPLE/USDT","stake_amount":99.097856,"max_stake_amount":99.097856,"amount":4331.2,"open_date":"2024-05-01 03:35:00+00:00","close_date":"2024-05-01 18:09:00+00:00","open_rate":0.02288,"close_rate":0.023154834834834832,"fee_open":0.001,"fee_close":0.001,"trade_duration":874,"profit_ratio":0.00999000999000999,"profit_abs":0.99097856,"exit_reason":"roi","initial_stop_loss_abs":0.01716,"initial_stop_loss_ratio":-0.25,"stop_loss_abs":0.01716,"stop_loss_ratio":-0.25,"min_rate":0.02097,"max_rate":0.02317,"is_open":false,"enter_tag":"","leverage":1.0,"is_short":false,"open_timestamp":1714534500000,"close_timestamp":1714586940000,"orders":[{"amount":4331.2,"safe_price":0.02288,"ft_order_side":"buy","order_filled_timestamp":1714534500000,"ft_is_entry":true,"ft_order_tag":""},{"amount":4331.2,"safe_price":0.023154834834834832,"ft_order_side":"sell","order_filled_timestamp":1714586940000,"ft_is_entry":false,"ft_order_tag":"roi"}]},{"pair":"XLM/USDT","stake_amount":99.0075,"max_stake_amount":99.0075,"amount":921.0,"open_date":"2024-05-01 03:35:00+00:00","close_date":"2024-05-01 18:05:00+00:00","open_rate":0.1075,"close_rate":0.10879129129129128,"fee_open":0.001,"fee_close":0.001,"trade_duration":870,"profit_ratio":0.00999000999000999,"profit_abs":0.990075,"exit_reason":"roi","initial_stop_loss_abs":0.0807,"initial_stop_loss_ratio":-0.25,"stop_loss_abs":0.0807,"stop_loss_ratio":-0.25,"min_rate":0.1031,"max_rate":0.1089,"is_open":false,"enter_tag":"","leverage":1.0,"is_short":false,"open_timestamp":1714534500000,"close_timestamp":1714586700000,"orders":[{"amount":921.0,"safe_price":0.1075,"ft_order_side":"buy","order_filled_timestamp":1714534500000,"ft_is_entry":true,"ft_order_tag":""},{"amount":921.0,"safe_price":0.10879129129129128,"ft_order_side":"sell","order_filled_timestamp":1714586700000,"ft_is_entry":false,"ft_order_tag":"roi"}]},{"pair":"POND/USDT","stake_amount":100.0331,"max_stake_amount":100.0331,"amount":5542.0,"open_date":"2024-05-01 18:05:00+00:00","close_date":"2024-05-01 18:34:00+00:00","open_rate":0.01805,"close_rate":0.018266816816816817,"fee_open":0.001,"fee_close":0.001,"trade_duration":29,"profit_ratio":0.009990009990009992,"profit_abs":1.000331,"exit_reason":"roi","initial_stop_loss_abs":0.01354,"initial_stop_loss_ratio":-0.25,"stop_loss_abs":0.01354,"stop_loss_ratio":-0.25,"min_rate":0.018,"max_rate":0.01827,"is_open":false,"enter_tag":"","leverage":1.0,"is_short":false,"open_timestamp":1714586700000,"close_timestamp":1714588440000,"orders":[{"amount":5542.0,"safe_price":0.01805,"ft_order_side":"buy","order_filled_timestamp":1714586700000,"ft_is_entry":true,"ft_order_tag":""},{"amount":5542.0,"safe_price":0.018266816816816817,"ft_order_side":"sell","order_filled_timestamp":1714588440000,"ft_is_entry":false,"ft_order_tag":"roi"}]},{"pair":"BTC/USDT","stake_amount":99.8150228,"max_stake_amount":99.8150228,"amount":0.00172,"open_date":"2024-05-01 18:10:00+00:00","close_date":"2024-05-01 18:44:00+00:00","open_rate":58031.99,"close_rate":58729.070960960955,"fee_open":0.001,"fee_close":0.001,"trade_duration":34,"profit_ratio":0.009990010010027037,"profit_abs":0.99815023,"exit_reason":"roi","initial_stop_loss_abs":43524.0,"initial_stop_loss_ratio":-0.25,"stop_loss_abs":43524.0,"stop_loss_ratio":-0.25,"min_rate":57548.25,"max_rate":58741.19,"is_open":false,"enter_tag":"","leverage":1.0,"is_short":false,"open_timestamp":1714587000000,"close_timestamp":1714589040000,"orders":[{"amount":0.00172,"safe_price":58031.99,"ft_order_side":"buy","order_filled_timestamp":1714587000000,"ft_is_entry":true,"ft_order_tag":""},{"amount":0.00172,"safe_price":58729.070960960955,"ft_order_side":"sell","order_filled_timestamp":1714589040000,"ft_is_entry":false,"ft_order_tag":"roi"}]},{"pair":"ADA/USDT","stake_amount":100.12788,"max_stake_amount":100.12788,"amount":224.1,"open_date":"2024-05-01 18:30:00+00:00","close_date":"2024-05-01 18:43:00+00:00","open_rate":0.4468,"close_rate":0.45216696696696695,"fee_open":0.001,"fee_close":0.001,"trade_duration":13,"profit_ratio":0.009990009990009988,"profit_abs":1.0012788,"exit_reason":"roi","initial_stop_loss_abs":0.3351,"initial_stop_loss_ratio":-0.25,"stop_loss_abs":0.3351,"stop_loss_ratio":-0.25,"min_rate":0.4447,"max_rate":0.4527,"is_open":false,"enter_tag":"","leverage":1.0,"is_short":false,"open_timestamp":1714588200000,"close_timestamp":1714588980000,"orders":[{"amount":224.1,"safe_price":0.4468,"ft_order_side":"buy","order_filled_timestamp":1714588200000,"ft_is_entry":true,"ft_order_tag":""},{"amount":224.1,"safe_price":0.45216696696696695,"ft_order_side":"sell","order_filled_timestamp":1714588980000,"ft_is_entry":false,"ft_order_tag":"roi"}]},{"pair":"ALGO/USDT","stake_amount":100.3024,"max_stake_amount":100.3024,"amount":556.0,"open_date":"2024-05-01 18:40:00+00:00","close_date":"2024-05-01 18:44:00+00:00","open_rate":0.1804,"close_rate":0.18256696696696695,"fee_open":0.001,"fee_close":0.001,"trade_duration":4,"profit_ratio":0.00999000999000999,"profit_abs":1.003024,"exit_reason":"roi","initial_stop_loss_abs":0.1353,"initial_stop_loss_ratio":-0.25,"stop_loss_abs":0.1353,"stop_loss_ratio":-0.25,"min_rate":0.1802,"max_rate":0.183,"is_open":false,"enter_tag":"","leverage":1.0,"is_short":false,"open_timestamp":1714588800000,"close_timestamp":1714589040000,"orders":[{"amount":556.0,"safe_price":0.1804,"ft_order_side":"buy","order_filled_timestamp":1714588800000,"ft_is_entry":true,"ft_order_tag":""},{"amount":556.0,"safe_price":0.18256696696696695,"ft_order_side":"sell","order_filled_timestamp":1714589040000,"ft_is_entry":false,"ft_order_tag":"roi"}]},{"pair":"AR/USDT","stake_amount":100.43383,"max_stake_amount":100.43383,"amount":3.43,"open_date":"2024-05-01 18:40:00+00:00","close_date":"2024-05-01 18:44:00+00:00","open_rate":29.281,"close_rate":29.632723723723718,"fee_open":0.001,"fee_close":0.001,"trade_duration":4,"profit_ratio":0.009990009990009988,"profit_abs":1.0043383,"exit_reason":"roi","initial_stop_loss_abs":21.97,"initial_stop_loss_ratio":-0.25,"stop_loss_abs":21.97,"stop_loss_ratio":-0.25,"min_rate":29.178,"max_rate":29.827,"is_open":false,"enter_tag":"","leverage":1.0,"is_short":false,"open_timestamp":1714588800000,"close_timestamp":1714589040000,"orders":[{"amount":3.43,"safe_price":29.281,"ft_order_side":"buy","order_filled_timestamp":1714588800000,"ft_is_entry":true,"ft_order_tag":""},{"amount":3.43,"safe_price":29.632723723723718,"ft_order_side":"sell","order_filled_timestamp":1714589040000,"ft_is_entry":false,"ft_order_tag":"roi"}]},{"pair":"SUSHI/USDT","stake_amount":98.9241,"max_stake_amount":98.9241,"amount":102.3,"open_date":"2024-05-01 03:20:00+00:00","close_date":"2024-05-01 18:52:00+00:00","open_rate":0.967,"close_rate":0.9786156156156155,"fee_open":0.001,"fee_close":0.001,"trade_duration":932,"profit_ratio":0.00999000999000999,"profit_abs":0.989241,"exit_reason":"roi","initial_stop_loss_abs":0.726,"initial_stop_loss_ratio":-0.25,"stop_loss_abs":0.726,"stop_loss_ratio":-0.25,"min_rate":0.9,"max_rate":0.982,"is_open":false,"enter_tag":"","leverage":1.0,"is_short":false,"open_timestamp":1714533600000,"close_timestamp":1714589520000,"orders":[{"amount":102.3,"safe_price":0.967,"ft_order_side":"buy","order_filled_timestamp":1714533600000,"ft_is_entry":true,"ft_order_tag":""},{"amount":102.3,"safe_price":0.9786156156156155,"ft_order_side":"sell","order_filled_timestamp":1714589520000,"ft_is_entry":false,"ft_order_tag":"roi"}]},{"pair":"AAVE/USDT","stake_amount":99.12637,"max_stake_amount":99.12637,"amount":1.187,"open_date":"2024-05-01 04:00:00+00:00","close_date":"2024-05-01 18:52:00+00:00","open_rate":83.51,"close_rate":84.51312312312311,"fee_open":0.001,"fee_close":0.001,"trade_duration":892,"profit_ratio":0.00999000999000999,"profit_abs":0.9912637,"exit_reason":"roi","initial_stop_loss_abs":62.64,"initial_stop_loss_ratio":-0.25,"stop_loss_abs":62.64,"stop_loss_ratio":-0.25,"min_rate":78.52,"max_rate":84.52,"is_open":false,"enter_tag":"","leverage":1.0,"is_short":false,"open_timestamp":1714536000000,"close_timestamp":1714589520000,"orders":[{"amount":1.187,"safe_price":83.51,"ft_order_side":"buy","order_filled_timestamp":1714536000000,"ft_is_entry":true,"ft_order_tag":""},{"amount":1.187,"safe_price":84.51312312312311,"ft_order_side":"sell","order_filled_timestamp":1714589520000,"ft_is_entry":false,"ft_order_tag":"roi"}]},{"pair":"LDO/USDT","stake_amount":100.035,"max_stake_amount":100.035,"amount":51.3,"open_date":"2024-05-01 18:05:00+00:00","close_date":"2024-05-01 18:50:00+00:00","open_rate":1.95,"close_rate":1.9734234234234231,"fee_open":0.001,"fee_close":0.001,"trade_duration":45,"profit_ratio":0.00999000999000999,"profit_abs":1.00035,"exit_reason":"roi","initial_stop_loss_abs":1.463,"initial_stop_loss_ratio":-0.25,"stop_loss_abs":1.463,"stop_loss_ratio":-0.25,"min_rate":1.922,"max_rate":1.978,"is_open":false,"enter_tag":"","leverage":1.0,"is_short":false,"open_timestamp":1714586700000,"close_timestamp":1714589400000,"orders":[{"amount":51.3,"safe_price":1.95,"ft_order_side":"buy","order_filled_timestamp":1714586700000,"ft_is_entry":true,"ft_order_tag":""},{"amount":51.3,"safe_price":1.9734234234234231,"ft_order_side":"sell","order_filled_timestamp":1714589400000,"ft_is_entry":false,"ft_order_tag":"roi"}]},{"pair":"BTC/USDT","stake_amount":100.3574376,"max_stake_amount":100.3574376,"amount":0.00171,"open_date":"2024-05-01 18:50:00+00:00","close_date":"2024-05-01 18:53:00+00:00","open_rate":58688.56,"close_rate":59393.52768768768,"fee_open":0.001,"fee_close":0.001,"trade_duration":3,"profit_ratio":0.009990010029827709,"profit_abs":1.00357438,"exit_reason":"roi","initial_stop_loss_abs":44016.42,"initial_stop_loss_ratio":-0.25,"stop_loss_abs":44016.42,"stop_loss_ratio":-0.25,"min_rate":58688.56,"max_rate":59424.01,"is_open":false,"enter_tag":"","leverage":1.0,"is_short":false,"open_timestamp":1714589400000,"close_timestamp":1714589580000,"orders":[{"amount":0.00171,"safe_price":58688.56,"ft_order_side":"buy","order_filled_timestamp":1714589400000,"ft_is_entry":true,"ft_order_tag":""},{"amount":0.00171,"safe_price":59393.52768768768,"ft_order_side":"sell","order_filled_timestamp":1714589580000,"ft_is_entry":false,"ft_order_tag":"roi"}]},{"pair":"ATOM/USDT","stake_amount":99.45558,"max_stake_amount":99.45558,"amount":11.62,"open_date":"2024-05-01 04:50:00+00:00","close_date":"2024-05-01 22:25:00+00:00","open_rate":8.559,"close_rate":8.661810810810808,"fee_open":0.001,"fee_close":0.001,"trade_duration":1055,"profit_ratio":0.00999000999000999,"profit_abs":0.9945558,"exit_reason":"roi","initial_stop_loss_abs":6.42,"initial_stop_loss_ratio":-0.25,"stop_loss_abs":6.42,"stop_loss_ratio":-0.25,"min_rate":8.021,"max_rate":8.674,"is_open":false,"enter_tag":"","leverage":1.0,"is_short":false,"open_timestamp":1714539000000,"close_timestamp":1714602300000,"orders":[{"amount":11.62,"safe_price":8.559,"ft_order_side":"buy","order_filled_timestamp":1714539000000,"ft_is_entry":true,"ft_order_tag":""},{"amount":11.62,"safe_price":8.661810810810808,"ft_order_side":"sell","order_filled_timestamp":1714602300000,"ft_is_entry":false,"ft_order_tag":"roi"}]},{"pair":"BAT/USDT","stake_amount":100.4032,"max_stake_amount":100.4032,"amount":424.0,"open_date":"2024-05-01 18:45:00+00:00","close_date":"2024-05-01 23:34:00+00:00","open_rate":0.2368,"close_rate":0.23964444444444444,"fee_open":0.001,"fee_close":0.001,"trade_duration":289,"profit_ratio":0.00999000999000999,"profit_abs":1.004032,"exit_reason":"roi","initial_stop_loss_abs":0.1776,"initial_stop_loss_ratio":-0.25,"stop_loss_abs":0.1776,"stop_loss_ratio":-0.25,"min_rate":0.2312,"max_rate":0.2399,"is_open":false,"enter_tag":"","leverage":1.0,"is_short":false,"open_timestamp":1714589100000,"close_timestamp":1714606440000,"orders":[{"amount":424.0,"safe_price":0.2368,"ft_order_side":"buy","order_filled_timestamp":1714589100000,"ft_is_entry":true,"ft_order_tag":""},{"amount":424.0,"safe_price":0.23964444444444444,"ft_order_side":"sell","order_filled_timestamp":1714606440000,"ft_is_entry":false,"ft_order_tag":"roi"}]},{"pair":"APT/USDT","stake_amount":100.9528,"max_stake_amount":100.9528,"amount":11.42,"open_date":"2024-05-01 22:25:00+00:00","close_date":"2024-05-01 23:41:00+00:00","open_rate":8.84,"close_rate":8.946186186186186,"fee_open":0.001,"fee_close":0.001,"trade_duration":76,"profit_ratio":0.00999000999000999,"profit_abs":1.009528,"exit_reason":"roi","initial_stop_loss_abs":6.63,"initial_stop_loss_ratio":-0.25,"stop_loss_abs":6.63,"stop_loss_ratio":-0.25,"min_rate":8.83,"max_rate":8.95,"is_open":false,"enter_tag":"","leverage":1.0,"is_short":false,"open_timestamp":1714602300000,"close_timestamp":1714606860000,"orders":[{"amount":11.42,"safe_price":8.84,"ft_order_side":"buy","order_filled_timestamp":1714602300000,"ft_is_entry":true,"ft_order_tag":""},{"amount":11.42,"safe_price":8.946186186186186,"ft_order_side":"sell","order_filled_timestamp":1714606860000,"ft_is_entry":false,"ft_order_tag":"roi"}]},{"pair":"AVAX/USDT","stake_amount":101.08,"max_stake_amount":101.08,"amount":3.04,"open_date":"2024-05-01 23:40:00+00:00","close_date":"2024-05-02 00:00:00+00:00","open_rate":33.25,"close_rate":33.6493993993994,"fee_open":0.001,"fee_close":0.001,"trade_duration":20,"profit_ratio":0.00999000999000999,"profit_abs":1.0108,"exit_reason":"roi","initial_stop_loss_abs":24.94,"initial_stop_loss_ratio":-0.25,"stop_loss_abs":24.94,"stop_loss_ratio":-0.25,"min_rate":33.23,"max_rate":33.74,"is_open":false,"enter_tag":"","leverage":1.0,"is_short":false,"open_timestamp":1714606800000,"close_timestamp":1714608000000,"orders":[{"amount":3.04,"safe_price":33.25,"ft_order_side":"buy","order_filled_timestamp":1714606800000,"ft_is_entry":true,"ft_order_tag":""},{"amount":3.04,"safe_price":33.6493993993994,"ft_order_side":"sell","order_filled_timestamp":1714608000000,"ft_is_entry":false,"ft_order_tag":"roi"}]},{"pair":"ALGO/USDT","stake_amount":100.7172,"max_stake_amount":100.7172,"amount":554.0,"open_date":"2024-05-01 18:50:00+00:00","close_date":"2024-05-02 00:00:00+00:00","open_rate":0.1818,"close_rate":0.1807,"fee_open":0.001,"fee_close":0.001,"trade_duration":310,"profit_ratio":-0.008036517937508036,"profit_abs":-0.810225,"exit_reason":"force_exit","initial_stop_loss_abs":0.1364,"initial_stop_loss_ratio":-0.25,"stop_loss_abs":0.1364,"stop_loss_ratio":-0.25,"min_rate":0.1762,"max_rate":0.1834,"is_open":false,"enter_tag":"","leverage":1.0,"is_short":false,"open_timestamp":1714589400000,"close_timestamp":1714608000000,"orders":[{"amount":554.0,"safe_price":0.1818,"ft_order_side":"buy","order_filled_timestamp":1714589400000,"ft_is_entry":true,"ft_order_tag":""},{"amount":554.0,"safe_price":0.1807,"ft_order_side":"sell","order_filled_timestamp":1714608000000,"ft_is_entry":false,"ft_order_tag":"force_exit"}]},{"pair":"ARB/USDT","stake_amount":100.52328,"max_stake_amount":100.52328,"amount":95.7,"open_date":"2024-05-01 18:45:00+00:00","close_date":"2024-05-02 00:00:00+00:00","open_rate":1.0504,"close_rate":1.0295,"fee_open":0.001,"fee_close":0.001,"trade_duration":315,"profit_ratio":-0.021855429414454546,"profit_abs":-2.19917643,"exit_reason":"force_exit","initial_stop_loss_abs":0.7879,"initial_stop_loss_ratio":-0.25,"stop_loss_abs":0.7879,"stop_loss_ratio":-0.25,"min_rate":1.0114,"max_rate":1.0579,"is_open":false,"enter_tag":"","leverage":1.0,"is_short":false,"open_timestamp":1714589100000,"close_timestamp":1714608000000,"orders":[{"amount":95.7,"safe_price":1.0504,"ft_order_side":"buy","order_filled_timestamp":1714589100000,"ft_is_entry":true,"ft_order_tag":""},{"amount":95.7,"safe_price":1.0295,"ft_order_side":"sell","order_filled_timestamp":1714608000000,"ft_is_entry":false,"ft_order_tag":"force_exit"}]},{"pair":"AUDIO/USDT","stake_amount":99.0864,"max_stake_amount":99.0864,"amount":589.8,"open_date":"2024-05-01 03:40:00+00:00","close_date":"2024-05-02 00:00:00+00:00","open_rate":0.168,"close_rate":0.1673,"fee_open":0.001,"fee_close":0.001,"trade_duration":1220,"profit_ratio":-0.0061563436563436555,"profit_abs":-0.61061994,"exit_reason":"force_exit","initial_stop_loss_abs":0.126,"initial_stop_loss_ratio":-0.25,"stop_loss_abs":0.126,"stop_loss_ratio":-0.25,"min_rate":0.1564,"max_rate":0.1698,"is_open":false,"enter_tag":"","leverage":1.0,"is_short":false,"open_timestamp":1714534800000,"close_timestamp":1714608000000,"orders":[{"amount":589.8,"safe_price":0.168,"ft_order_side":"buy","order_filled_timestamp":1714534800000,"ft_is_entry":true,"ft_order_tag":""},{"amount":589.8,"safe_price":0.1673,"ft_order_side":"sell","order_filled_timestamp":1714608000000,"ft_is_entry":false,"ft_order_tag":"force_exit"}]},{"pair":"ATOM/USDT","stake_amount":101.04629,"max_stake_amount":101.04629,"amount":11.51,"open_date":"2024-05-01 23:35:00+00:00","close_date":"2024-05-02 00:00:00+00:00","open_rate":8.779,"close_rate":8.742,"fee_open":0.001,"fee_close":0.001,"trade_duration":25,"profit_ratio":-0.006204184242685211,"profit_abs":-0.62753671,"exit_reason":"force_exit","initial_stop_loss_abs":6.585,"initial_stop_loss_ratio":-0.25,"stop_loss_abs":6.585,"stop_loss_ratio":-0.25,"min_rate":8.724,"max_rate":8.805,"is_open":false,"enter_tag":"","leverage":1.0,"is_short":false,"open_timestamp":1714606500000,"close_timestamp":1714608000000,"orders":[{"amount":11.51,"safe_price":8.779,"ft_order_side":"buy","order_filled_timestamp":1714606500000,"ft_is_entry":true,"ft_order_tag":""},{"amount":11.51,"safe_price":8.742,"ft_order_side":"sell","order_filled_timestamp":1714608000000,"ft_is_entry":false,"ft_order_tag":"force_exit"}]},{"pair":"BCH/USDT","stake_amount":100.536,"max_stake_amount":100.536,"amount":0.236,"open_date":"2024-05-01 18:50:00+00:00","close_date":"2024-05-02 00:00:00+00:00","open_rate":426.0,"close_rate":424.7,"fee_open":0.001,"fee_close":0.001,"trade_duration":310,"profit_ratio":-0.00504354800129448,"profit_abs":-0.5075652,"exit_reason":"force_exit","initial_stop_loss_abs":319.5,"initial_stop_loss_ratio":-0.25,"stop_loss_abs":319.5,"stop_loss_ratio":-0.25,"min_rate":411.2,"max_rate":431.1,"is_open":false,"enter_tag":"","leverage":1.0,"is_short":false,"open_timestamp":1714589400000,"close_timestamp":1714608000000,"orders":[{"amount":0.236,"safe_price":426.0,"ft_order_side":"buy","order_filled_timestamp":1714589400000,"ft_is_entry":true,"ft_order_tag":""},{"amount":0.236,"safe_price":424.7,"ft_order_side":"sell","order_filled_timestamp":1714608000000,"ft_is_entry":false,"ft_order_tag":"force_exit"}]},{"pair":"BNB/USDT","stake_amount":98.7796,"max_stake_amount":98.7796,"amount":0.172,"open_date":"2024-05-01 03:40:00+00:00","close_date":"2024-05-02 00:00:00+00:00","open_rate":574.3,"close_rate":561.8,"fee_open":0.001,"fee_close":0.001,"trade_duration":1220,"profit_ratio":-0.023720141951031733,"profit_abs":-2.3454092,"exit_reason":"force_exit","initial_stop_loss_abs":430.73,"initial_stop_loss_ratio":-0.25,"stop_loss_abs":430.73,"stop_loss_ratio":-0.25,"min_rate":536.7,"max_rate":575.7,"is_open":false,"enter_tag":"","leverage":1.0,"is_short":false,"open_timestamp":1714534800000,"close_timestamp":1714608000000,"orders":[{"amount":0.172,"safe_price":574.3,"ft_order_side":"buy","order_filled_timestamp":1714534800000,"ft_is_entry":true,"ft_order_tag":""},{"amount":0.172,"safe_price":561.8,"ft_order_side":"sell","order_filled_timestamp":1714608000000,"ft_is_entry":false,"ft_order_tag":"force_exit"}]},{"pair":"DOGE/USDT","stake_amount":99.06096,"max_stake_amount":99.06096,"amount":752.0,"open_date":"2024-05-01 03:35:00+00:00","close_date":"2024-05-02 00:00:00+00:00","open_rate":0.13173,"close_rate":0.13021,"fee_open":0.001,"fee_close":0.001,"trade_duration":1225,"profit_ratio":-0.013513701056402035,"profit_abs":-1.34001888,"exit_reason":"force_exit","initial_stop_loss_abs":0.0988,"initial_stop_loss_ratio":-0.25,"stop_loss_abs":0.0988,"stop_loss_ratio":-0.25,"min_rate":0.1201,"max_rate":0.13329,"is_open":false,"enter_tag":"","leverage":1.0,"is_short":false,"open_timestamp":1714534500000,"close_timestamp":1714608000000,"orders":[{"amount":752.0,"safe_price":0.13173,"ft_order_side":"buy","order_filled_timestamp":1714534500000,"ft_is_entry":true,"ft_order_tag":""},{"amount":752.0,"safe_price":0.13021,"ft_order_side":"sell","order_filled_timestamp":1714608000000,"ft_is_entry":false,"ft_order_tag":"force_exit"}]},{"pair":"LDO/USDT","stake_amount":100.929,"max_stake_amount":100.929,"amount":51.0,"open_date":"2024-05-01 18:55:00+00:00","close_date":"2024-05-02 00:00:00+00:00","open_rate":1.979,"close_rate":1.941,"fee_open":0.001,"fee_close":0.001,"trade_duration":305,"profit_ratio":-0.021161254107186396,"profit_abs":-2.13792,"exit_reason":"force_exit","initial_stop_loss_abs":1.485,"initial_stop_loss_ratio":-0.25,"stop_loss_abs":1.485,"stop_loss_ratio":-0.25,"min_rate":1.877,"max_rate":1.979,"is_open":false,"enter_tag":"","leverage":1.0,"is_short":false,"open_timestamp":1714589700000,"close_timestamp":1714608000000,"orders":[{"amount":51.0,"safe_price":1.979,"ft_order_side":"buy","order_filled_timestamp":1714589700000,"ft_is_entry":true,"ft_order_tag":""},{"amount":51.0,"safe_price":1.941,"ft_order_side":"sell","order_filled_timestamp":1714608000000,"ft_is_entry":false,"ft_order_tag":"force_exit"}]},{"pair":"TRX/USDT","stake_amount":98.988474,"max_stake_amount":98.988474,"amount":822.3,"open_date":"2024-05-01 02:50:00+00:00","close_date":"2024-05-02 00:00:00+00:00","open_rate":0.12038,"close_rate":0.12044,"fee_open":0.001,"fee_close":0.001,"trade_duration":1270,"profit_ratio":-0.0015005762211239891,"profit_abs":-0.14868829,"exit_reason":"force_exit","initial_stop_loss_abs":0.0903,"initial_stop_loss_ratio":-0.25,"stop_loss_abs":0.0903,"stop_loss_ratio":-0.25,"min_rate":0.11718,"max_rate":0.12106,"is_open":false,"enter_tag":"","leverage":1.0,"is_short":false,"open_timestamp":1714531800000,"close_timestamp":1714608000000,"orders":[{"amount":822.3,"safe_price":0.12038,"ft_order_side":"buy","order_filled_timestamp":1714531800000,"ft_is_entry":true,"ft_order_tag":""},{"amount":822.3,"safe_price":0.12044,"ft_order_side":"sell","order_filled_timestamp":1714608000000,"ft_is_entry":false,"ft_order_tag":"force_exit"}]}],"locks":[],"best_pair":{"key":"BTC/USDT","trades":2,"profit_mean":0.009990010019927373,"profit_mean_pct":1.0,"profit_sum":0.019980020039854746,"profit_sum_pct":2.0,"profit_total_abs":2.00172461,"profit_total":0.00200172461,"profit_total_pct":0.2,"duration_avg":"0:18:00","wins":2,"draws":0,"losses":0,"winrate":1.0},"worst_pair":{"key":"BNB/USDT","trades":1,"profit_mean":-0.023720141951031733,"profit_mean_pct":-2.37,"profit_sum":-0.023720141951031733,"profit_sum_pct":-2.37,"profit_total_abs":-2.3454092,"profit_total":-0.0023454092,"profit_total_pct":-0.23,"duration_avg":"20:20:00","wins":0,"draws":0,"losses":1,"winrate":0.0},"results_per_pair":[{"key":"AVAX/USDT","trades":2,"profit_mean":0.00999000999000999,"profit_mean_pct":1.0,"profit_sum":0.01998001998001998,"profit_sum_pct":2.0,"profit_total_abs":2.004994,"profit_total":0.002004994,"profit_total_pct":0.2,"duration_avg":"1:02:00","wins":2,"draws":0,"losses":0,"winrate":1.0},{"key":"BTC/USDT","trades":2,"profit_mean":0.009990010019927373,"profit_mean_pct":1.0,"profit_sum":0.019980020039854746,"profit_sum_pct":2.0,"profit_total_abs":2.00172461,"profit_total":0.00200172461,"profit_total_pct":0.2,"duration_avg":"0:18:00","wins":2,"draws":0,"losses":0,"winrate":1.0},{"key":"ADA/USDT","trades":3,"profit_mean":0.005244417592322054,"profit_mean_pct":0.52,"profit_sum":0.01573325277696616,"profit_sum_pct":1.57,"profit_total_abs":1.5761950599999999,"profit_total":0.0015761950599999998,"profit_total_pct":0.16,"duration_avg":"2:57:00","wins":2,"draws":0,"losses":1,"winrate":0.6666666666666666},{"key":"ATOM/USDT","trades":3,"profit_mean":0.004591945245778256,"profit_mean_pct":0.46,"profit_sum":0.01377583573733477,"profit_sum_pct":1.38,"profit_total_abs":1.35754409,"profit_total":0.0013575440899999999,"profit_total_pct":0.14,"duration_avg":"6:12:00","wins":2,"draws":0,"losses":1,"winrate":0.6666666666666666},{"key":"APT/USDT","trades":1,"profit_mean":0.00999000999000999,"profit_mean_pct":1.0,"profit_sum":0.00999000999000999,"profit_sum_pct":1.0,"profit_total_abs":1.009528,"profit_total":0.001009528,"profit_total_pct":0.1,"duration_avg":"1:16:00","wins":1,"draws":0,"losses":0,"winrate":1.0},{"key":"AR/USDT","trades":1,"profit_mean":0.009990009990009988,"profit_mean_pct":1.0,"profit_sum":0.009990009990009988,"profit_sum_pct":1.0,"profit_total_abs":1.0043383,"profit_total":0.0010043383,"profit_total_pct":0.1,"duration_avg":"0:04:00","wins":1,"draws":0,"losses":0,"winrate":1.0},{"key":"BAT/USDT","trades":1,"profit_mean":0.00999000999000999,"profit_mean_pct":1.0,"profit_sum":0.00999000999000999,"profit_sum_pct":1.0,"profit_total_abs":1.004032,"profit_total":0.001004032,"profit_total_pct":0.1,"duration_avg":"4:49:00","wins":1,"draws":0,"losses":0,"winrate":1.0},{"key":"POND/USDT","trades":1,"profit_mean":0.009990009990009992,"profit_mean_pct":1.0,"profit_sum":0.009990009990009992,"profit_sum_pct":1.0,"profit_total_abs":1.000331,"profit_total":0.0010003310000000001,"profit_total_pct":0.1,"duration_avg":"0:29:00","wins":1,"draws":0,"losses":0,"winrate":1.0},{"key":"BURGER/USDT","trades":1,"profit_mean":0.009990009990009992,"profit_mean_pct":1.0,"profit_sum":0.009990009990009992,"profit_sum_pct":1.0,"profit_total_abs":0.996156,"profit_total":0.000996156,"profit_total_pct":0.1,"duration_avg":"0:16:00","wins":1,"draws":0,"losses":0,"winrate":1.0},{"key":"LTC/USDT","trades":1,"profit_mean":0.00999000999000999,"profit_mean_pct":1.0,"profit_sum":0.00999000999000999,"profit_sum_pct":1.0,"profit_total_abs":0.9951068,"profit_total":0.0009951068,"profit_total_pct":0.1,"duration_avg":"2:46:00","wins":1,"draws":0,"losses":0,"winrate":1.0},{"key":"AAVE/USDT","trades":1,"profit_mean":0.00999000999000999,"profit_mean_pct":1.0,"profit_sum":0.00999000999000999,"profit_sum_pct":1.0,"profit_total_abs":0.9912637,"profit_total":0.0009912637,"profit_total_pct":0.1,"duration_avg":"14:52:00","wins":1,"draws":0,"losses":0,"winrate":1.0},{"key":"PEOPLE/USDT","trades":1,"profit_mean":0.00999000999000999,"profit_mean_pct":1.0,"profit_sum":0.00999000999000999,"profit_sum_pct":1.0,"profit_total_abs":0.99097856,"profit_total":0.00099097856,"profit_total_pct":0.1,"duration_avg":"14:34:00","wins":1,"draws":0,"losses":0,"winrate":1.0},{"key":"XLM/USDT","trades":1,"profit_mean":0.00999000999000999,"profit_mean_pct":1.0,"profit_sum":0.00999000999000999,"profit_sum_pct":1.0,"profit_total_abs":0.990075,"profit_total":0.000990075,"profit_total_pct":0.1,"duration_avg":"14:30:00","wins":1,"draws":0,"losses":0,"winrate":1.0},{"key":"PEPE/USDT","trades":1,"profit_mean":0.009990010020282747,"profit_mean_pct":1.0,"profit_sum":0.009990010020282747,"profit_sum_pct":1.0,"profit_total_abs":0.99,"profit_total":0.00099,"profit_total_pct":0.1,"duration_avg":"0:24:00","wins":1,"draws":0,"losses":0,"winrate":1.0},{"key":"DOT/USDT","trades":1,"profit_mean":0.00999000999000999,"profit_mean_pct":1.0,"profit_sum":0.00999000999000999,"profit_sum_pct":1.0,"profit_total_abs":0.9898252,"profit_total":0.0009898252,"profit_total_pct":0.1,"duration_avg":"1:30:00","wins":1,"draws":0,"losses":0,"winrate":1.0},{"key":"FTM/USDT","trades":1,"profit_mean":0.009990009990009992,"profit_mean_pct":1.0,"profit_sum":0.009990009990009992,"profit_sum_pct":1.0,"profit_total_abs":0.9897,"profit_total":0.0009897,"profit_total_pct":0.1,"duration_avg":"0:50:00","wins":1,"draws":0,"losses":0,"winrate":1.0},{"key":"SUSHI/USDT","trades":1,"profit_mean":0.00999000999000999,"profit_mean_pct":1.0,"profit_sum":0.00999000999000999,"profit_sum_pct":1.0,"profit_total_abs":0.989241,"profit_total":0.000989241,"profit_total_pct":0.1,"duration_avg":"15:32:00","wins":1,"draws":0,"losses":0,"winrate":1.0},{"key":"ALGO/USDT","trades":2,"profit_mean":0.0009767460262509768,"profit_mean_pct":0.1,"profit_sum":0.0019534920525019536,"profit_sum_pct":0.2,"profit_total_abs":0.19279899999999994,"profit_total":0.00019279899999999995,"profit_total_pct":0.02,"duration_avg":"2:37:00","wins":1,"draws":0,"losses":1,"winrate":0.5},{"key":"ALICE/USDT","trades":0,"profit_mean":0.0,"profit_mean_pct":0.0,"profit_sum":0.0,"profit_sum_pct":0.0,"profit_total_abs":0.0,"profit_total":0.0,"profit_total_pct":0.0,"duration_avg":"0:00","wins":0,"draws":0,"losses":0,"winrate":0.0},{"key":"CAKE/USDT","trades":0,"profit_mean":0.0,"profit_mean_pct":0.0,"profit_sum":0.0,"profit_sum_pct":0.0,"profit_total_abs":0.0,"profit_total":0.0,"profit_total_pct":0.0,"duration_avg":"0:00","wins":0,"draws":0,"losses":0,"winrate":0.0},{"key":"CHZ/USDT","trades":0,"profit_mean":0.0,"profit_mean_pct":0.0,"profit_sum":0.0,"profit_sum_pct":0.0,"profit_total_abs":0.0,"profit_total":0.0,"profit_total_pct":0.0,"duration_avg":"0:00","wins":0,"draws":0,"losses":0,"winrate":0.0},{"key":"COMP/USDT","trades":0,"profit_mean":0.0,"profit_mean_pct":0.0,"profit_sum":0.0,"profit_sum_pct":0.0,"profit_total_abs":0.0,"profit_total":0.0,"profit_total_pct":0.0,"duration_avg":"0:00","wins":0,"draws":0,"losses":0,"winrate":0.0},{"key":"CRV/USDT","trades":0,"profit_mean":0.0,"profit_mean_pct":0.0,"profit_sum":0.0,"profit_sum_pct":0.0,"profit_total_abs":0.0,"profit_total":0.0,"profit_total_pct":0.0,"duration_avg":"0:00","wins":0,"draws":0,"losses":0,"winrate":0.0},{"key":"DAR/USDT","trades":0,"profit_mean":0.0,"profit_mean_pct":0.0,"profit_sum":0.0,"profit_sum_pct":0.0,"profit_total_abs":0.0,"profit_total":0.0,"profit_total_pct":0.0,"duration_avg":"0:00","wins":0,"draws":0,"losses":0,"winrate":0.0},{"key":"DASH/USDT","trades":0,"profit_mean":0.0,"profit_mean_pct":0.0,"profit_sum":0.0,"profit_sum_pct":0.0,"profit_total_abs":0.0,"profit_total":0.0,"profit_total_pct":0.0,"duration_avg":"0:00","wins":0,"draws":0,"losses":0,"winrate":0.0},{"key":"ETC/USDT","trades":0,"profit_mean":0.0,"profit_mean_pct":0.0,"profit_sum":0.0,"profit_sum_pct":0.0,"profit_total_abs":0.0,"profit_total":0.0,"profit_total_pct":0.0,"duration_avg":"0:00","wins":0,"draws":0,"losses":0,"winrate":0.0},{"key":"ETH/USDT","trades":0,"profit_mean":0.0,"profit_mean_pct":0.0,"profit_sum":0.0,"profit_sum_pct":0.0,"profit_total_abs":0.0,"profit_total":0.0,"profit_total_pct":0.0,"duration_avg":"0:00","wins":0,"draws":0,"losses":0,"winrate":0.0},{"key":"FET/USDT","trades":0,"profit_mean":0.0,"profit_mean_pct":0.0,"profit_sum":0.0,"profit_sum_pct":0.0,"profit_total_abs":0.0,"profit_total":0.0,"profit_total_pct":0.0,"duration_avg":"0:00","wins":0,"draws":0,"losses":0,"winrate":0.0},{"key":"GALA/USDT","trades":0,"profit_mean":0.0,"profit_mean_pct":0.0,"profit_sum":0.0,"profit_sum_pct":0.0,"profit_total_abs":0.0,"profit_total":0.0,"profit_total_pct":0.0,"duration_avg":"0:00","wins":0,"draws":0,"losses":0,"winrate":0.0},{"key":"GHST/USDT","trades":0,"profit_mean":0.0,"profit_mean_pct":0.0,"profit_sum":0.0,"profit_sum_pct":0.0,"profit_total_abs":0.0,"profit_total":0.0,"profit_total_pct":0.0,"duration_avg":"0:00","wins":0,"draws":0,"losses":0,"winrate":0.0},{"key":"HIGH/USDT","trades":0,"profit_mean":0.0,"profit_mean_pct":0.0,"profit_sum":0.0,"profit_sum_pct":0.0,"profit_total_abs":0.0,"profit_total":0.0,"profit_total_pct":0.0,"duration_avg":"0:00","wins":0,"draws":0,"losses":0,"winrate":0.0},{"key":"ICP/USDT","trades":0,"profit_mean":0.0,"profit_mean_pct":0.0,"profit_sum":0.0,"profit_sum_pct":0.0,"profit_total_abs":0.0,"profit_total":0.0,"profit_total_pct":0.0,"duration_avg":"0:00","wins":0,"draws":0,"losses":0,"winrate":0.0},{"key":"JASMY/USDT","trades":0,"profit_mean":0.0,"profit_mean_pct":0.0,"profit_sum":0.0,"profit_sum_pct":0.0,"profit_total_abs":0.0,"profit_total":0.0,"profit_total_pct":0.0,"duration_avg":"0:00","wins":0,"draws":0,"losses":0,"winrate":0.0},{"key":"LINA/USDT","trades":0,"profit_mean":0.0,"profit_mean_pct":0.0,"profit_sum":0.0,"profit_sum_pct":0.0,"profit_total_abs":0.0,"profit_total":0.0,"profit_total_pct":0.0,"duration_avg":"0:00","wins":0,"draws":0,"losses":0,"winrate":0.0},{"key":"LINK/USDT","trades":0,"profit_mean":0.0,"profit_mean_pct":0.0,"profit_sum":0.0,"profit_sum_pct":0.0,"profit_total_abs":0.0,"profit_total":0.0,"profit_total_pct":0.0,"duration_avg":"0:00","wins":0,"draws":0,"losses":0,"winrate":0.0},{"key":"MANA/USDT","trades":0,"profit_mean":0.0,"profit_mean_pct":0.0,"profit_sum":0.0,"profit_sum_pct":0.0,"profit_total_abs":0.0,"profit_total":0.0,"profit_total_pct":0.0,"duration_avg":"0:00","wins":0,"draws":0,"losses":0,"winrate":0.0},{"key":"NEAR/USDT","trades":0,"profit_mean":0.0,"profit_mean_pct":0.0,"profit_sum":0.0,"profit_sum_pct":0.0,"profit_total_abs":0.0,"profit_total":0.0,"profit_total_pct":0.0,"duration_avg":"0:00","wins":0,"draws":0,"losses":0,"winrate":0.0},{"key":"OM/USDT","trades":0,"profit_mean":0.0,"profit_mean_pct":0.0,"profit_sum":0.0,"profit_sum_pct":0.0,"profit_total_abs":0.0,"profit_total":0.0,"profit_total_pct":0.0,"duration_avg":"0:00","wins":0,"draws":0,"losses":0,"winrate":0.0},{"key":"ONE/USDT","trades":0,"profit_mean":0.0,"profit_mean_pct":0.0,"profit_sum":0.0,"profit_sum_pct":0.0,"profit_total_abs":0.0,"profit_total":0.0,"profit_total_pct":0.0,"duration_avg":"0:00","wins":0,"draws":0,"losses":0,"winrate":0.0},{"key":"OP/USDT","trades":0,"profit_mean":0.0,"profit_mean_pct":0.0,"profit_sum":0.0,"profit_sum_pct":0.0,"profit_total_abs":0.0,"profit_total":0.0,"profit_total_pct":0.0,"duration_avg":"0:00","wins":0,"draws":0,"losses":0,"winrate":0.0},{"key":"PYR/USDT","trades":0,"profit_mean":0.0,"profit_mean_pct":0.0,"profit_sum":0.0,"profit_sum_pct":0.0,"profit_total_abs":0.0,"profit_total":0.0,"profit_total_pct":0.0,"duration_avg":"0:00","wins":0,"draws":0,"losses":0,"winrate":0.0},{"key":"ROSE/USDT","trades":0,"profit_mean":0.0,"profit_mean_pct":0.0,"profit_sum":0.0,"profit_sum_pct":0.0,"profit_total_abs":0.0,"profit_total":0.0,"profit_total_pct":0.0,"duration_avg":"0:00","wins":0,"draws":0,"losses":0,"winrate":0.0},{"key":"RUNE/USDT","trades":0,"profit_mean":0.0,"profit_mean_pct":0.0,"profit_sum":0.0,"profit_sum_pct":0.0,"profit_total_abs":0.0,"profit_total":0.0,"profit_total_pct":0.0,"duration_avg":"0:00","wins":0,"draws":0,"losses":0,"winrate":0.0},{"key":"SUPER/USDT","trades":0,"profit_mean":0.0,"profit_mean_pct":0.0,"profit_sum":0.0,"profit_sum_pct":0.0,"profit_total_abs":0.0,"profit_total":0.0,"profit_total_pct":0.0,"duration_avg":"0:00","wins":0,"draws":0,"losses":0,"winrate":0.0},{"key":"SHIB/USDT","trades":0,"profit_mean":0.0,"profit_mean_pct":0.0,"profit_sum":0.0,"profit_sum_pct":0.0,"profit_total_abs":0.0,"profit_total":0.0,"profit_total_pct":0.0,"duration_avg":"0:00","wins":0,"draws":0,"losses":0,"winrate":0.0},{"key":"SLP/USDT","trades":0,"profit_mean":0.0,"profit_mean_pct":0.0,"profit_sum":0.0,"profit_sum_pct":0.0,"profit_total_abs":0.0,"profit_total":0.0,"profit_total_pct":0.0,"duration_avg":"0:00","wins":0,"draws":0,"losses":0,"winrate":0.0},{"key":"SOL/USDT","trades":0,"profit_mean":0.0,"profit_mean_pct":0.0,"profit_sum":0.0,"profit_sum_pct":0.0,"profit_total_abs":0.0,"profit_total":0.0,"profit_total_pct":0.0,"duration_avg":"0:00","wins":0,"draws":0,"losses":0,"winrate":0.0},{"key":"SPELL/USDT","trades":0,"profit_mean":0.0,"profit_mean_pct":0.0,"profit_sum":0.0,"profit_sum_pct":0.0,"profit_total_abs":0.0,"profit_total":0.0,"profit_total_pct":0.0,"duration_avg":"0:00","wins":0,"draws":0,"losses":0,"winrate":0.0},{"key":"STX/USDT","trades":0,"profit_mean":0.0,"profit_mean_pct":0.0,"profit_sum":0.0,"profit_sum_pct":0.0,"profit_total_abs":0.0,"profit_total":0.0,"profit_total_pct":0.0,"duration_avg":"0:00","wins":0,"draws":0,"losses":0,"winrate":0.0},{"key":"SUI/USDT","trades":0,"profit_mean":0.0,"profit_mean_pct":0.0,"profit_sum":0.0,"profit_sum_pct":0.0,"profit_total_abs":0.0,"profit_total":0.0,"profit_total_pct":0.0,"duration_avg":"0:00","wins":0,"draws":0,"losses":0,"winrate":0.0},{"key":"TLM/USDT","trades":0,"profit_mean":0.0,"profit_mean_pct":0.0,"profit_sum":0.0,"profit_sum_pct":0.0,"profit_total_abs":0.0,"profit_total":0.0,"profit_total_pct":0.0,"duration_avg":"0:00","wins":0,"draws":0,"losses":0,"winrate":0.0},{"key":"XRP/USDT","trades":0,"profit_mean":0.0,"profit_mean_pct":0.0,"profit_sum":0.0,"profit_sum_pct":0.0,"profit_total_abs":0.0,"profit_total":0.0,"profit_total_pct":0.0,"duration_avg":"0:00","wins":0,"draws":0,"losses":0,"winrate":0.0},{"key":"YFI/USDT","trades":0,"profit_mean":0.0,"profit_mean_pct":0.0,"profit_sum":0.0,"profit_sum_pct":0.0,"profit_total_abs":0.0,"profit_total":0.0,"profit_total_pct":0.0,"duration_avg":"0:00","wins":0,"draws":0,"losses":0,"winrate":0.0},{"key":"YGG/USDT","trades":0,"profit_mean":0.0,"profit_mean_pct":0.0,"profit_sum":0.0,"profit_sum_pct":0.0,"profit_total_abs":0.0,"profit_total":0.0,"profit_total_pct":0.0,"duration_avg":"0:00","wins":0,"draws":0,"losses":0,"winrate":0.0},{"key":"ZRX/USDT","trades":0,"profit_mean":0.0,"profit_mean_pct":0.0,"profit_sum":0.0,"profit_sum_pct":0.0,"profit_total_abs":0.0,"profit_total":0.0,"profit_total_pct":0.0,"duration_avg":"0:00","wins":0,"draws":0,"losses":0,"winrate":0.0},{"key":"TRX/USDT","trades":1,"profit_mean":-0.0015005762211239891,"profit_mean_pct":-0.15,"profit_sum":-0.0015005762211239891,"profit_sum_pct":-0.15,"profit_total_abs":-0.14868829,"profit_total":-0.00014868829,"profit_total_pct":-0.01,"duration_avg":"21:10:00","wins":0,"draws":0,"losses":1,"winrate":0.0},{"key":"BCH/USDT","trades":1,"profit_mean":-0.00504354800129448,"profit_mean_pct":-0.5,"profit_sum":-0.00504354800129448,"profit_sum_pct":-0.5,"profit_total_abs":-0.5075652,"profit_total":-0.0005075652,"profit_total_pct":-0.05,"duration_avg":"5:10:00","wins":0,"draws":0,"losses":1,"winrate":0.0},{"key":"AUDIO/USDT","trades":1,"profit_mean":-0.0061563436563436555,"profit_mean_pct":-0.62,"profit_sum":-0.0061563436563436555,"profit_sum_pct":-0.62,"profit_total_abs":-0.61061994,"profit_total":-0.00061061994,"profit_total_pct":-0.06,"duration_avg":"20:20:00","wins":0,"draws":0,"losses":1,"winrate":0.0},{"key":"LDO/USDT","trades":2,"profit_mean":-0.005585622058588203,"profit_mean_pct":-0.56,"profit_sum":-0.011171244117176406,"profit_sum_pct":-1.12,"profit_total_abs":-1.1375699999999997,"profit_total":-0.0011375699999999996,"profit_total_pct":-0.11,"duration_avg":"2:55:00","wins":1,"draws":0,"losses":1,"winrate":0.5},{"key":"ARB/USDT","trades":2,"profit_mean":-0.005932709712222278,"profit_mean_pct":-0.59,"profit_sum":-0.011865419424444556,"profit_sum_pct":-1.19,"profit_total_abs":-1.20664763,"profit_total":-0.00120664763,"profit_total_pct":-0.12,"duration_avg":"3:00:00","wins":1,"draws":0,"losses":1,"winrate":0.5},{"key":"DOGE/USDT","trades":1,"profit_mean":-0.013513701056402035,"profit_mean_pct":-1.35,"profit_sum":-0.013513701056402035,"profit_sum_pct":-1.35,"profit_total_abs":-1.34001888,"profit_total":-0.0013400188799999998,"profit_total_pct":-0.13,"duration_avg":"20:25:00","wins":0,"draws":0,"losses":1,"winrate":0.0},{"key":"BNB/USDT","trades":1,"profit_mean":-0.023720141951031733,"profit_mean_pct":-2.37,"profit_sum":-0.023720141951031733,"profit_sum_pct":-2.37,"profit_total_abs":-2.3454092,"profit_total":-0.0023454092,"profit_total_pct":-0.23,"duration_avg":"20:20:00","wins":0,"draws":0,"losses":1,"winrate":0.0},{"key":"TOTAL","trades":34,"profit_mean":0.003774169884095982,"profit_mean_pct":0.38,"profit_sum":0.1283217760592634,"profit_sum_pct":12.83,"profit_total_abs":12.77731318,"profit_total":0.01277731318,"profit_total_pct":1.28,"duration_avg":"6:04:00","wins":24,"draws":0,"losses":10,"winrate":0.7058823529411765}],"results_per_enter_tag":[{"key":"","trades":34,"profit_mean":0.003774169884095982,"profit_mean_pct":0.38,"profit_sum":0.1283217760592634,"profit_sum_pct":12.83,"profit_total_abs":12.77731318,"profit_total":0.01277731318,"profit_total_pct":1.28,"duration_avg":"6:04:00","wins":24,"draws":0,"losses":10,"winrate":0.7058823529411765},{"key":"TOTAL","trades":34,"profit_mean":0.003774169884095982,"profit_mean_pct":0.38,"profit_sum":0.1283217760592634,"profit_sum_pct":12.83,"profit_total_abs":12.77731318,"profit_total":0.01277731318,"profit_total_pct":1.28,"duration_avg":"6:04:00","wins":24,"draws":0,"losses":10,"winrate":0.7058823529411765}],"exit_reason_summary":[{"key":"roi","trades":24,"profit_mean":0.00999000999376447,"profit_mean_pct":1.0,"profit_sum":0.23976023985034728,"profit_sum_pct":23.98,"profit_total_abs":23.926882569999997,"profit_total":0.023926882569999995,"profit_total_pct":2.39,"duration_avg":"3:56:00","wins":24,"draws":0,"losses":0,"winrate":1.0},{"key":"exit_signal","trades":1,"profit_mean":-0.004246767203053818,"profit_mean_pct":-0.42,"profit_sum":-0.004246767203053818,"profit_sum_pct":-0.42,"profit_total_abs":-0.42240974,"profit_total":-0.00042240973999999997,"profit_total_pct":-0.04,"duration_avg":"8:35:00","wins":0,"draws":0,"losses":1,"winrate":0.0},{"key":"force_exit","trades":9,"profit_mean":-0.011910188509781119,"profit_mean_pct":-1.19,"profit_sum":-0.10719169658803007,"profit_sum_pct":-10.72,"profit_total_abs":-10.727159650000003,"profit_total":-0.010727159650000002,"profit_total_pct":-1.07,"duration_avg":"11:29:00","wins":0,"draws":0,"losses":9,"winrate":0.0},{"key":"TOTAL","trades":34,"profit_mean":0.003774169884095982,"profit_mean_pct":0.38,"profit_sum":0.1283217760592634,"profit_sum_pct":12.83,"profit_total_abs":12.77731318,"profit_total":0.01277731318,"profit_total_pct":1.28,"duration_avg":"6:04:00","wins":24,"draws":0,"losses":10,"winrate":0.7058823529411765}],"mix_tag_stats":[{"key":["","roi"],"trades":24,"profit_mean":0.00999000999376447,"profit_mean_pct":1.0,"profit_sum":0.23976023985034728,"profit_sum_pct":23.98,"profit_total_abs":23.926882569999997,"profit_total":0.023926882569999995,"profit_total_pct":2.39,"duration_avg":"3:56:00","wins":24,"draws":0,"losses":0,"winrate":1.0},{"key":["","exit_signal"],"trades":1,"profit_mean":-0.004246767203053818,"profit_mean_pct":-0.42,"profit_sum":-0.004246767203053818,"profit_sum_pct":-0.42,"profit_total_abs":-0.42240974,"profit_total":-0.00042240973999999997,"profit_total_pct":-0.04,"duration_avg":"8:35:00","wins":0,"draws":0,"losses":1,"winrate":0.0},{"key":["","force_exit"],"trades":9,"profit_mean":-0.011910188509781119,"profit_mean_pct":-1.19,"profit_sum":-0.10719169658803007,"profit_sum_pct":-10.72,"profit_total_abs":-10.727159650000003,"profit_total":-0.010727159650000002,"profit_total_pct":-1.07,"duration_avg":"11:29:00","wins":0,"draws":0,"losses":9,"winrate":0.0},{"key":"TOTAL","trades":34,"profit_mean":0.003774169884095982,"profit_mean_pct":0.38,"profit_sum":0.1283217760592634,"profit_sum_pct":12.83,"profit_total_abs":12.77731318,"profit_total":0.01277731318,"profit_total_pct":1.28,"duration_avg":"6:04:00","wins":24,"draws":0,"losses":10,"winrate":0.7058823529411765}],"left_open_trades":[{"key":"TRX/USDT","trades":1,"profit_mean":-0.0015005762211239891,"profit_mean_pct":-0.15,"profit_sum":-0.0015005762211239891,"profit_sum_pct":-0.15,"profit_total_abs":-0.14868829,"profit_total":-0.00014868829,"profit_total_pct":-0.01,"duration_avg":"21:10:00","wins":0,"draws":0,"losses":1,"winrate":0.0},{"key":"BCH/USDT","trades":1,"profit_mean":-0.00504354800129448,"profit_mean_pct":-0.5,"profit_sum":-0.00504354800129448,"profit_sum_pct":-0.5,"profit_total_abs":-0.5075652,"profit_total":-0.0005075652,"profit_total_pct":-0.05,"duration_avg":"5:10:00","wins":0,"draws":0,"losses":1,"winrate":0.0},{"key":"AUDIO/USDT","trades":1,"profit_mean":-0.0061563436563436555,"profit_mean_pct":-0.62,"profit_sum":-0.0061563436563436555,"profit_sum_pct":-0.62,"profit_total_abs":-0.61061994,"profit_total":-0.00061061994,"profit_total_pct":-0.06,"duration_avg":"20:20:00","wins":0,"draws":0,"losses":1,"winrate":0.0},{"key":"ATOM/USDT","trades":1,"profit_mean":-0.006204184242685211,"profit_mean_pct":-0.62,"profit_sum":-0.006204184242685211,"profit_sum_pct":-0.62,"profit_total_abs":-0.62753671,"profit_total":-0.00062753671,"profit_total_pct":-0.06,"duration_avg":"0:25:00","wins":0,"draws":0,"losses":1,"winrate":0.0},{"key":"ALGO/USDT","trades":1,"profit_mean":-0.008036517937508036,"profit_mean_pct":-0.8,"profit_sum":-0.008036517937508036,"profit_sum_pct":-0.8,"profit_total_abs":-0.810225,"profit_total":-0.0008102249999999999,"profit_total_pct":-0.08,"duration_avg":"5:10:00","wins":0,"draws":0,"losses":1,"winrate":0.0},{"key":"DOGE/USDT","trades":1,"profit_mean":-0.013513701056402035,"profit_mean_pct":-1.35,"profit_sum":-0.013513701056402035,"profit_sum_pct":-1.35,"profit_total_abs":-1.34001888,"profit_total":-0.0013400188799999998,"profit_total_pct":-0.13,"duration_avg":"20:25:00","wins":0,"draws":0,"losses":1,"winrate":0.0},{"key":"LDO/USDT","trades":1,"profit_mean":-0.021161254107186396,"profit_mean_pct":-2.12,"profit_sum":-0.021161254107186396,"profit_sum_pct":-2.12,"profit_total_abs":-2.13792,"profit_total":-0.0021379199999999998,"profit_total_pct":-0.21,"duration_avg":"5:05:00","wins":0,"draws":0,"losses":1,"winrate":0.0},{"key":"ARB/USDT","trades":1,"profit_mean":-0.021855429414454546,"profit_mean_pct":-2.19,"profit_sum":-0.021855429414454546,"profit_sum_pct":-2.19,"profit_total_abs":-2.19917643,"profit_total":-0.00219917643,"profit_total_pct":-0.22,"duration_avg":"5:15:00","wins":0,"draws":0,"losses":1,"winrate":0.0},{"key":"BNB/USDT","trades":1,"profit_mean":-0.023720141951031733,"profit_mean_pct":-2.37,"profit_sum":-0.023720141951031733,"profit_sum_pct":-2.37,"profit_total_abs":-2.3454092,"profit_total":-0.0023454092,"profit_total_pct":-0.23,"duration_avg":"20:20:00","wins":0,"draws":0,"losses":1,"winrate":0.0},{"key":"TOTAL","trades":9,"profit_mean":-0.011910188509781119,"profit_mean_pct":-1.19,"profit_sum":-0.10719169658803007,"profit_sum_pct":-10.72,"profit_total_abs":-10.727159650000003,"profit_total":-0.010727159650000002,"profit_total_pct":-1.07,"duration_avg":"11:29:00","wins":0,"draws":0,"losses":9,"winrate":0.0}],"total_trades":34,"trade_count_long":34,"trade_count_short":0,"total_volume":3391.7222801,"avg_stake_amount":99.75653765,"profit_mean":0.003774169884095982,"profit_median":0.00999000999000999,"profit_total":0.01277731318,"profit_total_long":0.01277731318,"profit_total_short":0.0,"profit_total_abs":12.77731318,"profit_total_long_abs":12.77731318,"profit_total_short_abs":0.0,"cagr":101.94303749550294,"expectancy":0.37580332882352935,"expectancy_ratio":0.3370563612623334,"sortino":311.18519861910045,"sharpe":232.0123840094987,"calmar":2568.8752792773957,"profit_factor":2.145991628291933,"backtest_start":"2024-05-01 00:00:00","backtest_start_ts":1714521600000,"backtest_end":"2024-05-02 00:00:00","backtest_end_ts":1714608000000,"backtest_days":1,"backtest_run_start_ts":1735578242,"backtest_run_end_ts":1735578251,"trades_per_day":34.0,"market_change":0.017179513725521095,"pairlist":["AAVE/USDT","ADA/USDT","ALGO/USDT","ALICE/USDT","APT/USDT","AR/USDT","ARB/USDT","AUDIO/USDT","ATOM/USDT","AVAX/USDT","BAT/USDT","BCH/USDT","BNB/USDT","BTC/USDT","BURGER/USDT","CAKE/USDT","CHZ/USDT","COMP/USDT","CRV/USDT","DAR/USDT","DASH/USDT","DOGE/USDT","DOT/USDT","ETC/USDT","ETH/USDT","FET/USDT","FTM/USDT","GALA/USDT","GHST/USDT","HIGH/USDT","ICP/USDT","JASMY/USDT","LDO/USDT","LINA/USDT","LINK/USDT","LTC/USDT","MANA/USDT","NEAR/USDT","OM/USDT","ONE/USDT","OP/USDT","PEOPLE/USDT","PEPE/USDT","POND/USDT","PYR/USDT","ROSE/USDT","RUNE/USDT","SUPER/USDT","SHIB/USDT","SLP/USDT","SOL/USDT","SPELL/USDT","STX/USDT","SUI/USDT","SUSHI/USDT","TLM/USDT","TRX/USDT","XLM/USDT","XRP/USDT","YFI/USDT","YGG/USDT","ZRX/USDT"],"stake_amount":"unlimited","stake_currency":"USDT","stake_currency_decimals":3,"starting_balance":1000,"dry_run_wallet":1000,"final_balance":1012.77731318,"rejected_signals":1032,"timedout_entry_orders":0,"timedout_exit_orders":0,"canceled_trade_entries":0,"canceled_entry_orders":0,"replaced_entry_orders":0,"max_open_trades":10,"max_open_trades_setting":10,"timeframe":"5m","timeframe_detail":"1m","timerange":"20240501-20240502","enable_protections":true,"strategy_name":"Simple","stoploss":-0.25,"trailing_stop":false,"trailing_stop_positive":null,"trailing_stop_positive_offset":0.0,"trailing_only_offset_is_reached":false,"use_custom_stoploss":false,"minimal_roi":{"0":0.01},"use_exit_signal":true,"exit_profit_only":false,"exit_profit_offset":0.0,"ignore_roi_if_entry_signal":false,"trading_mode":"spot","margin_mode":"","periodic_breakdown":{"day":[{"date":"01/05/2024","date_ts":1714521600000,"profit_abs":22.49367283,"wins":23,"draws":0,"loses":1,"winrate":0.9583333333333334},{"date":"02/05/2024","date_ts":1714608000000,"profit_abs":-9.71635965,"wins":1,"draws":0,"loses":9,"winrate":0.1}],"week":[{"date":"06/05/2024","date_ts":1714953600000,"profit_abs":12.77731318,"wins":24,"draws":0,"loses":10,"winrate":0.7058823529411765}],"month":[{"date":"31/05/2024","date_ts":1717113600000,"profit_abs":12.77731318,"wins":24,"draws":0,"loses":10,"winrate":0.7058823529411765}]},"backtest_best_day":0.22552346265728349,"backtest_worst_day":-0.09720168659802009,"backtest_best_day_abs":22.49367283,"backtest_worst_day_abs":-9.71635965,"winning_days":1,"draw_days":0,"losing_days":1,"daily_profit":[["2024-05-01",22.49367283],["2024-05-02",-9.71635965]],"wins":24,"losses":10,"draws":0,"winrate":0.7058823529411765,"holding_avg":"6:04:00","holding_avg_s":21840.0,"winner_holding_avg":"3:56:00","winner_holding_avg_s":14160.0,"loser_holding_avg":"11:12:00","loser_holding_avg_s":40320.0,"max_consecutive_wins":19,"max_consecutive_losses":9,"max_drawdown_account":0.009502611026538368,"max_relative_drawdown":0.009502611026538368,"max_drawdown_abs":9.716359649999998,"drawdown_start":"2024-05-01 23:41:00","drawdown_start_ts":1714606860000.0,"drawdown_end":"2024-05-02 00:00:00","drawdown_end_ts":1714608000000.0,"max_drawdown_low":12.777313180000004,"max_drawdown_high":22.49367283,"csum_min":1000.99,"csum_max":1023.50447283}},"strategy_comparison":[{"key":"Simple","trades":34,"profit_mean":0.003774169884095982,"profit_mean_pct":0.38,"profit_sum":0.1283217760592634,"profit_sum_pct":12.83,"profit_total_abs":12.77731318,"profit_total":0.01277731318,"profit_total_pct":1.28,"duration_avg":"6:04:00","wins":24,"draws":0,"losses":10,"winrate":0.7058823529411765,"max_drawdown_account":0.009502611026538368,"max_drawdown_abs":"9.716"}]}